art/__init__.py
art/art-example.py
art/test.py
art/train.py
art/train1.py
art_python-0.0.5.dist-info/DESCRIPTION.rst
art_python-0.0.5.dist-info/METADATA
art_python-0.0.5.dist-info/RECORD
art_python-0.0.5.dist-info/WHEEL
art_python-0.0.5.dist-info/metadata.json
art_python-0.0.5.dist-info/top_level.txt
