Metadata-Version: 2.0
Name: art-python
Version: 0.0.5
Summary: Python package
Home-page: https://github.com/cbirkj/art-python
Author: ART Developers
Author-email: cbirkjones@gmail.com
License: MIT
Platform: UNKNOWN
Requires-Dist: numpy (>=1.10.4)
Requires-Dist: pandas (>=0.18.0)
